csvreportcreater/__init__.py
csvreportcreater/__main__.py
csvreportcreater/proc.py
csvreportcreater-0.1.0.dist-info/METADATA
csvreportcreater-0.1.0.dist-info/WHEEL
csvreportcreater-0.1.0.dist-info/entry_points.txt
csvreportcreater-0.1.0.dist-info/top_level.txt
csvreportcreater-0.1.0.dist-info/RECORD
