Metadata-Version: 2.1
Name: csvreportcreater
Version: 0.1.0
Summary: A package for create csv report
Author-email: Dusya <Lev.khrobostov@mail.ru>
License: MIT
